Topsis/__init__.py
Topsis/__main__.py
Topsis_Aditya_102103546-1.0.8.dist-info/LICENSE
Topsis_Aditya_102103546-1.0.8.dist-info/METADATA
Topsis_Aditya_102103546-1.0.8.dist-info/WHEEL
Topsis_Aditya_102103546-1.0.8.dist-info/entry_points.txt
Topsis_Aditya_102103546-1.0.8.dist-info/top_level.txt
Topsis_Aditya_102103546-1.0.8.dist-info/RECORD
