Metadata-Version: 2.1
Name: Topsis_Aditya_102103546
Version: 1.0.8
Summary: This Python script implements the TOPSIS (Technique for Order Preference by Similarity to Ideal Solution) algorithm.
Home-page: https://github.com/BROWNcoder4946/Topsis_pypi_package
Author: Aditya Vashishta
Author-email: adityavashishta3911@gmail.com
License: MIT
Classifier: License :: OSI Approved :: MIT License
Classifier: Programming Language :: Python :: 3.6
Classifier: Programming Language :: Python :: 3.7
Classifier: Programming Language :: Python :: 3.8
Classifier: Programming Language :: Python :: 3.9
Classifier: Programming Language :: Python :: 3.10
Classifier: Programming Language :: Python :: 3.11
Classifier: Programming Language :: Python :: 3.12
License-File: LICENSE
Requires-Dist: pandas
Requires-Dist: numpy
